matopt/__init__.py
matopt/aml/__init__.py
matopt/aml/desc.py
matopt/aml/expr.py
matopt/aml/model.py
matopt/aml/rule.py
matopt/aml/util.py
matopt/materials/__init__.py
matopt/materials/atom.py
matopt/materials/bblock.py
matopt/materials/canvas.py
matopt/materials/design.py
matopt/materials/geometry.py
matopt/materials/motifs.py
matopt/materials/tiling.py
matopt/materials/transform_func.py
matopt/materials/util.py
matopt/materials/lattices/__init__.py
matopt/materials/lattices/bcc_lattice.py
matopt/materials/lattices/cubic_lattice.py
matopt/materials/lattices/diamond_lattice.py
matopt/materials/lattices/fcc_lattice.py
matopt/materials/lattices/hcp_lattice.py
matopt/materials/lattices/lattice.py
matopt/materials/lattices/perovskite_lattice.py
matopt/materials/lattices/unit_cell_lattice.py
matopt/materials/lattices/wurtzite_lattice.py
matopt/materials/parsers/CFG.py
matopt/materials/parsers/PDB.py
matopt/materials/parsers/POSCAR.py
matopt/materials/parsers/XYZ.py
matopt/materials/parsers/__init__.py
matopt/materials/parsers/pymatgen.py
matopt-0.0.1.dist-info/METADATA
matopt-0.0.1.dist-info/WHEEL
matopt-0.0.1.dist-info/licenses/LICENSE.md
matopt-0.0.1.dist-info/RECORD
