Metadata-Version: 2.3
Name: matopt
Version: 0.0.1
Summary: Materials Design via Mathematical Optimization
Project-URL: Homepage, https://github.com/xyin-anl/matopt
Project-URL: Bug Tracker, https://github.com/xyin-anl/matopt/issues
Author-email: Shawn Yin <shawn.pypi@gmail.com>
Classifier: Operating System :: OS Independent
Classifier: Programming Language :: Python :: 3
Requires-Python: >=3.9
Requires-Dist: numpy
Requires-Dist: pyomo
